{
  "Version": "2012-10-17",
  "Statement": [
    {
      "Sid": "VpcAndNetworking",
      "Effect": "Allow",
      "Action": [
        "ec2:CreateVpc",
        "ec2:DeleteVpc",
        "ec2:ModifyVpcAttribute",
        "ec2:CreateSubnet",
        "ec2:DeleteSubnet",
        "ec2:ModifySubnetAttribute",
        "ec2:CreateInternetGateway",
        "ec2:DeleteInternetGateway",
        "ec2:AttachInternetGateway",
        "ec2:DetachInternetGateway",
        "ec2:CreateNatGateway",
        "ec2:DeleteNatGateway",
        "ec2:AllocateAddress",
        "ec2:ReleaseAddress",
        "ec2:CreateRouteTable",
        "ec2:DeleteRouteTable",
        "ec2:CreateRoute",
        "ec2:DeleteRoute",
        "ec2:AssociateRouteTable",
        "ec2:DisassociateRouteTable",
        "ec2:CreateSecurityGroup",
        "ec2:DeleteSecurityGroup",
        "ec2:AuthorizeSecurityGroupIngress",
        "ec2:AuthorizeSecurityGroupEgress",
        "ec2:RevokeSecurityGroupIngress",
        "ec2:RevokeSecurityGroupEgress",
        "ec2:CreateTags",
        "ec2:DeleteTags",
        "ec2:Describe*"
      ],
      "Resource": "*"
    },
    {
      "Sid": "EcsCluster",
      "Effect": "Allow",
      "Action": [
        "ecs:CreateCluster",
        "ecs:DeleteCluster",
        "ecs:DescribeClusters",
        "ecs:ListClusters",
        "ecs:UpdateCluster",
        "ecs:PutClusterCapacityProviders",
        "ecs:TagResource",
        "ecs:UntagResource",
        "ecs:RegisterTaskDefinition",
        "ecs:DeregisterTaskDefinition",
        "ecs:DescribeTaskDefinition",
        "ecs:ListTaskDefinitions",
        "ecs:CreateService",
        "ecs:UpdateService",
        "ecs:DeleteService",
        "ecs:DescribeServices",
        "ecs:ListServices",
        "ecs:DescribeTasks",
        "ecs:ListTasks",
        "ecs:RunTask",
        "ecs:StopTask",
        "ecs:ExecuteCommand"
      ],
      "Resource": "*"
    },
    {
      "Sid": "Elbv2",
      "Effect": "Allow",
      "Action": [
        "elasticloadbalancing:CreateLoadBalancer",
        "elasticloadbalancing:DeleteLoadBalancer",
        "elasticloadbalancing:ModifyLoadBalancerAttributes",
        "elasticloadbalancing:CreateTargetGroup",
        "elasticloadbalancing:DeleteTargetGroup",
        "elasticloadbalancing:ModifyTargetGroup",
        "elasticloadbalancing:ModifyTargetGroupAttributes",
        "elasticloadbalancing:RegisterTargets",
        "elasticloadbalancing:DeregisterTargets",
        "elasticloadbalancing:CreateListener",
        "elasticloadbalancing:DeleteListener",
        "elasticloadbalancing:ModifyListener",
        "elasticloadbalancing:CreateRule",
        "elasticloadbalancing:DeleteRule",
        "elasticloadbalancing:ModifyRule",
        "elasticloadbalancing:AddTags",
        "elasticloadbalancing:RemoveTags",
        "elasticloadbalancing:Describe*"
      ],
      "Resource": "*"
    },
    {
      "Sid": "IamForEcsRolesAndPassRole",
      "Effect": "Allow",
      "Action": [
        "iam:CreateRole",
        "iam:DeleteRole",
        "iam:GetRole",
        "iam:PassRole",
        "iam:AttachRolePolicy",
        "iam:DetachRolePolicy",
        "iam:PutRolePolicy",
        "iam:DeleteRolePolicy",
        "iam:GetRolePolicy",
        "iam:ListRolePolicies",
        "iam:ListAttachedRolePolicies",
        "iam:TagRole",
        "iam:UntagRole",
        "iam:CreateServiceLinkedRole"
      ],
      "Resource": [
        "arn:aws:iam::*:role/kong-ecs-testbed-*",
        "arn:aws:iam::*:role/aws-service-role/ecs.amazonaws.com/*",
        "arn:aws:iam::*:role/aws-service-role/ecs.application-autoscaling.amazonaws.com/*",
        "arn:aws:iam::*:role/aws-service-role/elasticloadbalancing.amazonaws.com/*"
      ]
    },
    {
      "Sid": "CloudWatchLogs",
      "Effect": "Allow",
      "Action": [
        "logs:CreateLogGroup",
        "logs:DeleteLogGroup",
        "logs:DescribeLogGroups",
        "logs:DescribeLogStreams",
        "logs:PutRetentionPolicy",
        "logs:TagLogGroup",
        "logs:UntagLogGroup",
        "logs:TagResource",
        "logs:UntagResource",
        "logs:ListTagsForResource",
        "logs:GetLogEvents",
        "logs:FilterLogEvents"
      ],
      "Resource": "*"
    },
    {
      "Sid": "SecretsForKonnectCerts",
      "Effect": "Allow",
      "Action": [
        "secretsmanager:CreateSecret",
        "secretsmanager:DeleteSecret",
        "secretsmanager:DescribeSecret",
        "secretsmanager:GetSecretValue",
        "secretsmanager:PutSecretValue",
        "secretsmanager:UpdateSecret",
        "secretsmanager:TagResource",
        "secretsmanager:UntagResource",
        "secretsmanager:GetResourcePolicy",
        "secretsmanager:PutResourcePolicy",
        "secretsmanager:DeleteResourcePolicy"
      ],
      "Resource": "arn:aws:secretsmanager:*:*:secret:kong-ecs-testbed/*"
    },
    {
      "Sid": "ServiceDiscoveryOptional",
      "Effect": "Allow",
      "Action": [
        "servicediscovery:CreatePrivateDnsNamespace",
        "servicediscovery:DeleteNamespace",
        "servicediscovery:CreateService",
        "servicediscovery:DeleteService",
        "servicediscovery:GetNamespace",
        "servicediscovery:GetService",
        "servicediscovery:GetOperation",
        "servicediscovery:ListNamespaces",
        "servicediscovery:ListServices",
        "servicediscovery:ListTagsForResource",
        "servicediscovery:TagResource",
        "servicediscovery:UntagResource"
      ],
      "Resource": "*"
    },
    {
      "Sid": "Route53ForCloudMapPrivateZone",
      "Effect": "Allow",
      "Action": [
        "route53:CreateHostedZone",
        "route53:DeleteHostedZone",
        "route53:GetHostedZone",
        "route53:ListHostedZonesByName",
        "route53:ListHostedZonesByVPC",
        "route53:ChangeResourceRecordSets",
        "route53:ListResourceRecordSets",
        "route53:GetChange",
        "route53:AssociateVPCWithHostedZone",
        "route53:DisassociateVPCFromHostedZone",
        "route53:ChangeTagsForResource",
        "route53:ListTagsForResource"
      ],
      "Resource": "*"
    },
    {
      "Sid": "IamOidcProviderForGithub",
      "Effect": "Allow",
      "Action": "iam:*OpenIDConnect*",
      "Resource": "*"
    },
    {
      "Sid": "S3StateBucket",
      "Effect": "Allow",
      "Action": "s3:*",
      "Resource": [
        "arn:aws:s3:::kong-ecs-testbed-tfstate-*",
        "arn:aws:s3:::kong-ecs-testbed-tfstate-*/*"
      ]
    }
  ]
}
